CONTRIBUTORS
COPYING
MANIFEST.in
README.rst
setup.py
docs/done.rst
docs/pymacs_signalrecursion.patch
docs/ropemacs.rst
docs/todo.rst
ropemacs/__init__.py
ropemacs_py3k.egg-info/PKG-INFO
ropemacs_py3k.egg-info/SOURCES.txt
ropemacs_py3k.egg-info/dependency_links.txt
ropemacs_py3k.egg-info/requires.txt
ropemacs_py3k.egg-info/top_level.txt