Metadata-Version: 1.1
Name: ropemacs-py3k
Version: 0.7
Summary: An emacs mode for using rope python refactoring library for Python3
Home-page: https://github.com/atilaneves/ropemacs
Author: Atila Neves
Author-email: atila.neves@gmail.com
License: GNU GPL
Platform: UNKNOWN
Classifier: Development Status :: 4 - Beta
Classifier: Operating System :: OS Independent
Classifier: Environment :: X11 Applications
Classifier: Environment :: Win32 (MS Windows)
Classifier: Environment :: MacOS X
Classifier: Intended Audience :: Developers
Classifier: License :: OSI Approved :: GNU General Public License (GPL)
Classifier: Natural Language :: English
Classifier: Programming Language :: Python
Classifier: Topic :: Text Editors :: Emacs
Classifier: Topic :: Software Development
Requires: ropemode_py3k
